nillion_client_core-0.2.0.dist-info/METADATA
nillion_client_core-0.2.0.dist-info/WHEEL
nillion_client_core/__init__.py
nillion_client_core/__init__.pyi
nillion_client_core/py.typed
nillion_client_core/nillion_client_core.abi3.so
nillion_client_core-0.2.0.dist-info/RECORD
