Metadata-Version: 2.3
Name: nillion-client-core
Version: 0.2.0
Classifier: Programming Language :: Rust
Classifier: Programming Language :: Python :: Implementation :: CPython
Classifier: Programming Language :: Python :: Implementation :: PyPy
Requires-Dist: maturin[zig] ==1.7.4 ; extra == 'dev'
Requires-Dist: pip ==24.2 ; extra == 'dev'
Provides-Extra: dev
Requires-Python: >=3.10
